morseet/__init__.py
morseet/config.toml
morseet/convert.py
morseet/entry.py
morseet/main.py
morseet/morse_dict.py
morseet-1.0.0.dist-info/LICENSE
morseet-1.0.0.dist-info/METADATA
morseet-1.0.0.dist-info/WHEEL
morseet-1.0.0.dist-info/entry_points.txt
morseet-1.0.0.dist-info/top_level.txt
morseet-1.0.0.dist-info/RECORD
