Metadata-Version: 2.1
Name: morseet
Version: 1.0.0
Summary: morseet, is a command-line tool to convert morse code to text and vice versa.
Home-page: https://github.com/AnirudhG07/morseet
Author: Anirudh Gupta
Keywords: terminal,Morse Code converted,Encryption,CLI
Classifier: Development Status :: 5 - Production/Stable
Classifier: Intended Audience :: Developers
Classifier: Programming Language :: Python :: 3.11
Classifier: Programming Language :: Python :: 3.12
Classifier: Topic :: Games/Entertainment
Classifier: License :: OSI Approved :: Apache Software License
Classifier: Operating System :: POSIX
Classifier: Operating System :: MacOS
Classifier: Operating System :: Microsoft :: Windows
Requires-Python: >=3.11
License-File: LICENSE
Requires-Dist: toml
